{
    "$schema": "https://raw.githubusercontent.com/streetsidesoftware/cspell/main/cspell.schema.json",
    "import": [
        "@cspell/dict-ru_ru/cspell-ext.json"
    ],
    "dictionaries": [
        "ru-ru"
    ],
    "caseSensitive": false,
    "words": [
        "автодополнение",
        "автодополнения",
        "алерт",
        "алерта",
        "алерте",
        "алертом",
        "алерты",
        "бейджа",
        "булевый",
        "версионирование",
        "версионирования",
        "виджете",
        "виджетом",
        "гггг",
        "гига",
        "грид",
        "дедлайна",
        "дейтпикер",
        "деселект",
        "десктопное",
        "дизейблится",
        "дизейблятся",
        "дозаполнял",
        "дропдаун",
        "задизейбленные",
        "задизейблены",
        "задизейблится",
        "инлайн",
        "инпуте",
        "кастомизируемых",
        "кастомное",
        "кликает",
        "контрол",
        "контролам",
        "контролов",
        "контролы",
        "лейблами",
        "лейблы",
        "маркдауна",
        "матчер",
        "матчере",
        "межколонником",
        "миксинов",
        "модалка",
        "модалке",
        "модалки",
        "модалку",
        "нелистовом",
        "нелистовые",
        "нелистовым",
        "нелистовых",
        "плейсхолдер",
        "плейсхолдере",
        "подкатегорией",
        "подпапки",
        "поповер",
        "поповера",
        "поповере",
        "предзаполнить",
        "преднастроенных",
        "предустановка",
        "проскроллить",
        "псевдоссылка",
        "псевдоссылки",
        "псевдоссылку",
        "радиокнопок",
        "сайдпанелей",
        "сайдпанели",
        "сайдпанель",
        "селект",
        "селекта",
        "скролл",
        "скролла",
        "скроллбар",
        "скроллбара",
        "скроллбаров",
        "скролле",
        "спиннера",
        "спиннером",
        "спиннеры",
        "таймзон",
        "таймзоны",
        "таймпикер",
        "техдолг",
        "типографики",
        "типографику",
        "типографикой",
        "тултип",
        "тултипа",
        "тултипе",
        "тултипов",
        "тултипом",
        "тултипы",
        "ховер",
        "ховера",
        "ховеру",
        "чекбоксами",
        "чекбоксов",
        "чекбоксом",
        "чекбоксы"
    ]
}
